outsight/__init__.py
outsight/py.typed
outsight/stream.py
outsight/utils.py
outsight/ops/__init__.py
outsight/ops/combiners.py
outsight/ops/keyed.py
outsight/ops/misc.py
outsight/ops/queue.py
outsight/ops/reducers.py
outsight/ops/timing.py
outsight/run/__init__.py
outsight/run/core.py
outsight/run/exchange.py
outsight/run/fixtures.py
outsight-0.0.2.dist-info/METADATA
outsight-0.0.2.dist-info/WHEEL
outsight-0.0.2.dist-info/RECORD
