Metadata-Version: 2.4
Name: outsight
Version: 0.0.2
Summary: Iterate over what happens in your code
Requires-Python: >=3.10
Requires-Dist: asttokens>=3.0.0
Requires-Dist: varname>=0.14.0
